SSplines/__init__.py
SSplines/constants.py
SSplines/dicts.py
SSplines/helper_functions.py
SSplines/simplex_spline.py
SSplines/spline_function.py
SSplines/spline_space.py
SSplines/symbolic.py
ssplines-3.0.0.dist-info/METADATA
ssplines-3.0.0.dist-info/WHEEL
ssplines-3.0.0.dist-info/RECORD
