Metadata-Version: 2.4
Name: SSplines
Version: 3.0.0
Summary: A Python library for the evaluation of S-splines on the Powell-Sabin 12-split of a triangle.
Project-URL: Homepage, https://github.com/qTipTip/SSplines
Project-URL: Repository, https://github.com/qTipTip/SSplines
Project-URL: Documentation, https://github.com/qTipTip/SSplines
Project-URL: Bug Tracker, https://github.com/qTipTip/SSplines/issues
Project-URL: Changelog, https://github.com/qTipTip/SSplines/releases
Project-URL: Citation, https://doi.org/10.5281/zenodo.15742326
Author-email: Ivar Stangeby <istangeby@gmail.com>
License: MIT
Keywords: Powell-Sabin,computational-geometry,finite-element,interpolation,numerical-analysis,simplex-splines,splines
Classifier: Development Status :: 5 - Production/Stable
Classifier: Intended Audience :: Science/Research
Classifier: License :: OSI Approved :: MIT License
Classifier: Programming Language :: Python :: 3
Classifier: Programming Language :: Python :: 3.13
Classifier: Topic :: Scientific/Engineering :: Mathematics
Classifier: Topic :: Scientific/Engineering :: Physics
Requires-Python: >=3.13
Requires-Dist: numpy>=1.24.0
Requires-Dist: sympy>=1.10
Provides-Extra: dev
Requires-Dist: build; extra == 'dev'
Requires-Dist: matplotlib>=3.5.1; extra == 'dev'
Requires-Dist: pytest-cov; extra == 'dev'
Requires-Dist: pytest>=7.0.1; extra == 'dev'
Requires-Dist: twine; extra == 'dev'
